crane/__init__.py
crane/__version__.py
crane/arrow.py
crane/json.py
crane/core/__init__.py
crane/core/consumer.py
crane/core/iterables.py
crane/core/monitor.py
crane/core/sharding.py
crane/core/utils.py
crane/core/worker.py
crane/core/writer.py
crane/core/callbacks/__init__.py
crane/core/callbacks/base.py
crane/core/callbacks/tqdm_reporter.py
crane/core/runners/__init__.py
crane/core/runners/base.py
crane/core/runners/main_process_runner.py
crane/core/runners/multi_process_runner.py
crane/logging/__init__.py
crane/logging/formatter.py
crane/logging/setup.py
hyped_crane-0.1.3.dist-info/METADATA
hyped_crane-0.1.3.dist-info/WHEEL
hyped_crane-0.1.3.dist-info/top_level.txt
hyped_crane-0.1.3.dist-info/RECORD
