Metadata-Version: 2.4
Name: hyped-crane
Version: 0.1.3
Summary: Lift (process) and place (write) data streams, seamlessly and in parallel.
Author: open-hyped
License: Apache 2.0
Classifier: Programming Language :: Python :: 3.10
Classifier: Programming Language :: Python :: 3.11
Classifier: Programming Language :: Python :: 3.12
Requires-Python: >=3.10
Requires-Dist: dill>=0.3.8
Requires-Dist: orjson>=3.10.1
Requires-Dist: datasets>=4.0.0
Requires-Dist: fsspec<=2023.9.2
Requires-Dist: pyarrow>=17.0.0
Provides-Extra: linting
Requires-Dist: pre-commit; extra == "linting"
Provides-Extra: tests
Requires-Dist: pytest; extra == "tests"
Requires-Dist: pytest-cov; extra == "tests"
Requires-Dist: pytest-asyncio; extra == "tests"
Requires-Dist: pytest-integration; extra == "tests"
Provides-Extra: docs
Requires-Dist: sphinx; extra == "docs"
Requires-Dist: furo; extra == "docs"
